{
	"info": {
		"_postman_id": "2c501420-977f-4933-af09-6779e80d5d11",
		"name": "MECO API",
		"description": "Documentation for MECO API",
		"schema": "https://schema.getpostman.com/json/collection/v2.1.0/collection.json"
	},
	"item": [
		{
			"name": "Account",
			"item": [
				{
					"name": "Signin",
					"request": {
						"method": "POST",
						"header": [
							{
								"key": "Content-Type",
								"value": "application/json"
							},
							{
								"key": "User-Agent",
								"value": "User-Agent: Mozilla/5.0 (Macintosh; Intel Mac OS X 10_14_0) AppleWebKit/537.36 (KHTML, like Gecko) Chrome/71.0.3578.98 Safari/537.36",
								"type": "text"
							},
							{
								"key": "X-FORWARDED-FOR",
								"value": "196.245.163.202",
								"type": "text"
							}
						],
						"body": {
							"mode": "raw",
							"raw": "{\n\t\"username\": \"admin@email.com\",\n\t\"password\": \"password\"\n}"
						},
						"url": {
							"raw": "http://localhost:8080/accounts/signin",
							"protocol": "http",
							"host": [
								"localhost"
							],
							"port": "8080",
							"path": [
								"accounts",
								"signin"
							]
						}
					},
					"response": []
				},
				{
					"name": "Signup",
					"request": {
						"method": "POST",
						"header": [
							{
								"key": "Content-Type",
								"value": "application/json"
							}
						],
						"body": {
							"mode": "raw",
							"raw": "{\n\t\"username\": \"steve@email.com\",\n\t\"password\": \"password\"\n}"
						},
						"url": {
							"raw": "http://localhost:8080/accounts/signup",
							"protocol": "http",
							"host": [
								"localhost"
							],
							"port": "8080",
							"path": [
								"accounts",
								"signup"
							]
						}
					},
					"response": []
				},
				{
					"name": "Me",
					"request": {
						"method": "GET",
						"header": [
							{
								"key": "Authorization",
								"value": "Bearer TOKEN",
								"type": "text"
							}
						],
						"url": {
							"raw": "http://localhost:8080/accounts/me",
							"protocol": "http",
							"host": [
								"localhost"
							],
							"port": "8080",
							"path": [
								"accounts",
								"me"
							]
						}
					},
					"response": []
				},
				{
					"name": "Forgot Password",
					"request": {
						"method": "POST",
						"header": [],
						"url": {
							"raw": "http://localhost:8080/accounts/me/forgot?username=admin@email.com",
							"protocol": "http",
							"host": [
								"localhost"
							],
							"port": "8080",
							"path": [
								"accounts",
								"me",
								"forgot"
							],
							"query": [
								{
									"key": "username",
									"value": "admin@email.com"
								}
							]
						}
					},
					"response": []
				},
				{
					"name": "Reset Password",
					"request": {
						"method": "POST",
						"header": [],
						"body": {
							"mode": "raw",
							"raw": "{\n\t\"password\": \"password\"\n}",
							"options": {
								"raw": {
									"language": "json"
								}
							}
						},
						"url": {
							"raw": "http://localhost:8080/accounts/me/reset?token=TOKEN",
							"protocol": "http",
							"host": [
								"localhost"
							],
							"port": "8080",
							"path": [
								"accounts",
								"me",
								"reset"
							],
							"query": [
								{
									"key": "token",
									"value": "TOKEN"
								}
							]
						}
					},
					"response": []
				},
				{
					"name": "Update",
					"request": {
						"method": "PUT",
						"header": [
							{
								"key": "Content-Type",
								"value": "application/json"
							},
							{
								"key": "Authorization",
								"value": "Bearer TOKEN",
								"type": "text"
							},
							{
								"key": "User-Agent",
								"value": "User-Agent: Mozilla/5.0 (Macintosh; Intel Mac OS X 10_14_0) AppleWebKit/537.36 (KHTML, like Gecko) Chrome/71.0.3578.98 Safari/537.36",
								"type": "text"
							},
							{
								"key": "X-FORWARDED-FOR",
								"value": "196.245.163.202",
								"type": "text"
							}
						],
						"body": {
							"mode": "raw",
							"raw": "{\n    \"fullName\": \"Ash\",\n    \"emailSubscriptionEnabled\": false,\n    \"billingAlertEnabled\": true\n}"
						},
						"url": {
							"raw": "http://localhost:8080/accounts/me",
							"protocol": "http",
							"host": [
								"localhost"
							],
							"port": "8080",
							"path": [
								"accounts",
								"me"
							]
						}
					},
					"response": []
				},
				{
					"name": "Billing Logs",
					"request": {
						"method": "GET",
						"header": [
							{
								"key": "Authorization",
								"value": "Bearer TOKEN",
								"type": "text"
							}
						],
						"url": {
							"raw": "http://localhost:8080/accounts/me/billing/logs",
							"protocol": "http",
							"host": [
								"localhost"
							],
							"port": "8080",
							"path": [
								"accounts",
								"me",
								"billing",
								"logs"
							]
						}
					},
					"response": []
				},
				{
					"name": "Download Billing Logs",
					"request": {
						"method": "GET",
						"header": [
							{
								"key": "Authorization",
								"value": "Bearer TOKEN",
								"type": "text"
							}
						],
						"url": {
							"raw": "http://localhost:8080/accounts/me/billing/logs/download",
							"protocol": "http",
							"host": [
								"localhost"
							],
							"port": "8080",
							"path": [
								"accounts",
								"me",
								"billing",
								"logs",
								"download"
							]
						}
					},
					"response": []
				},
				{
					"name": "Security Logs",
					"request": {
						"method": "GET",
						"header": [
							{
								"key": "Authorization",
								"value": "Bearer TOKEN",
								"type": "text"
							}
						],
						"url": {
							"raw": "http://localhost:8080/accounts/me/security/logs",
							"protocol": "http",
							"host": [
								"localhost"
							],
							"port": "8080",
							"path": [
								"accounts",
								"me",
								"security",
								"logs"
							]
						}
					},
					"response": []
				},
				{
					"name": "Download Security Logs",
					"request": {
						"method": "GET",
						"header": [
							{
								"key": "Authorization",
								"value": "Bearer TOKEN",
								"type": "text"
							}
						],
						"url": {
							"raw": "http://localhost:8080/accounts/me/security/logs/download",
							"protocol": "http",
							"host": [
								"localhost"
							],
							"port": "8080",
							"path": [
								"accounts",
								"me",
								"security",
								"logs",
								"download"
							]
						}
					},
					"response": []
				}
			],
			"protocolProfileBehavior": {}
		},
		{
			"name": "API Key",
			"item": [
				{
					"name": "Find All",
					"request": {
						"method": "GET",
						"header": [
							{
								"key": "Authorization",
								"value": "Bearer TOKEN",
								"type": "text"
							}
						],
						"url": {
							"raw": "http://localhost:8080/api-keys",
							"protocol": "http",
							"host": [
								"localhost"
							],
							"port": "8080",
							"path": [
								"api-keys"
							]
						}
					},
					"response": []
				},
				{
					"name": "Create",
					"request": {
						"method": "POST",
						"header": [
							{
								"key": "Authorization",
								"value": "Bearer TOKEN",
								"type": "text"
							},
							{
								"key": "Content-Type",
								"value": "application/json",
								"type": "text"
							}
						],
						"body": {
							"mode": "raw",
							"raw": "{\n  \"name\": \"test key\",\n  \"enabled\": true,\n  \"scope\": {\n    \"image\": true,\n    \"gif\": false,\n    \"video\": true,\n    \"text\": false\n  },\n  \"accessPolicies\": [{\n  \t\"name\": \"newcastle\",\n  \t\"range\": \"127.0.0.1/32\"\n  }]\n}",
							"options": {
								"raw": {
									"language": "json"
								}
							}
						},
						"url": {
							"raw": "http://localhost:8080/api-keys",
							"protocol": "http",
							"host": [
								"localhost"
							],
							"port": "8080",
							"path": [
								"api-keys"
							]
						}
					},
					"response": []
				},
				{
					"name": "Update",
					"request": {
						"method": "PUT",
						"header": [
							{
								"key": "Authorization",
								"type": "text",
								"value": "Bearer TOKEN"
							},
							{
								"key": "Content-Type",
								"type": "text",
								"value": "application/json"
							}
						],
						"body": {
							"mode": "raw",
							"raw": "{\n  \"name\": \"updated key\",\n  \"enabled\": true,\n  \"scope\": {\n    \"image\": true,\n    \"gif\": false,\n    \"video\": true,\n    \"text\": false\n  },\n  \"accessPolicies\": [{\n  \t\"name\": \"newcastle\",\n  \t\"range\": \"127.0.0.1/32\"\n  }]\n}",
							"options": {
								"raw": {
									"language": "json"
								}
							}
						},
						"url": {
							"raw": "http://localhost:8080/api-keys/1",
							"protocol": "http",
							"host": [
								"localhost"
							],
							"port": "8080",
							"path": [
								"api-keys",
								"1"
							]
						}
					},
					"response": []
				},
				{
					"name": "Delete",
					"request": {
						"method": "DELETE",
						"header": [
							{
								"key": "Authorization",
								"type": "text",
								"value": "Bearer TOKEN"
							}
						],
						"body": {
							"mode": "raw",
							"raw": "",
							"options": {
								"raw": {
									"language": "json"
								}
							}
						},
						"url": {
							"raw": "http://localhost:8080/api-keys/1",
							"protocol": "http",
							"host": [
								"localhost"
							],
							"port": "8080",
							"path": [
								"api-keys",
								"1"
							]
						}
					},
					"response": []
				},
				{
					"name": "Logs",
					"protocolProfileBehavior": {
						"disableBodyPruning": true
					},
					"request": {
						"method": "GET",
						"header": [
							{
								"key": "Authorization",
								"type": "text",
								"value": "Bearer TOKEN"
							}
						],
						"body": {
							"mode": "raw",
							"raw": "",
							"options": {
								"raw": {
									"language": "json"
								}
							}
						},
						"url": {
							"raw": "http://localhost:8080/api-keys/1/logs",
							"protocol": "http",
							"host": [
								"localhost"
							],
							"port": "8080",
							"path": [
								"api-keys",
								"1",
								"logs"
							]
						}
					},
					"response": []
				},
				{
					"name": "Download Logs",
					"protocolProfileBehavior": {
						"disableBodyPruning": true
					},
					"request": {
						"method": "GET",
						"header": [
							{
								"key": "Authorization",
								"type": "text",
								"value": "Bearer TOKEN"
							}
						],
						"body": {
							"mode": "raw",
							"raw": "",
							"options": {
								"raw": {
									"language": "json"
								}
							}
						},
						"url": {
							"raw": "http://localhost:8080/api-keys/1/logs/download",
							"protocol": "http",
							"host": [
								"localhost"
							],
							"port": "8080",
							"path": [
								"api-keys",
								"1",
								"logs",
								"download"
							]
						}
					},
					"response": []
				}
			],
			"protocolProfileBehavior": {}
		}
	],
	"protocolProfileBehavior": {}
}